benchmark/__init__.py
benchmark/benchmark.py
tccm/__init__.py
tccm/api/__init__.py
tccm/api/client_option.py
tccm/api/metric.py
tccm/api/tccm_client.py
tccm/internal/__init__.py
tccm/internal/common/__init__.py
tccm/internal/common/business.py
tccm/internal/common/default.py
tccm/internal/common/util.py
tccm/internal/transport/__init__.py
tccm/internal/transport/transport.py
tccm/internal/version/__init__.py
tccm/internal/version/version.py
tccm/internal/work/__init__.py
tccm/internal/work/worker.py
tccm/pb/__init__.py
tccm/pb/sdk_metric_pb_pb2.py
tests/__init__.py
tests/client_test.py
tests/module_example.py
tests/simple_example.py
tccm_client_python-1.0.0.dist-info/LICENSE
tccm_client_python-1.0.0.dist-info/METADATA
tccm_client_python-1.0.0.dist-info/WHEEL
tccm_client_python-1.0.0.dist-info/top_level.txt
tccm_client_python-1.0.0.dist-info/RECORD
