Metadata-Version: 2.1
Name: tccm-client-python
Version: 1.0.0
Summary: tccm-client-python
Home-page: https://git.woa.com/cm-metrics/tccm-client-python
Author: zianazhao
Author-email: UNKNOWN
License: MIT
Platform: UNKNOWN
